invokust/__init__.py
invokust/loadtest.py
invokust/settings.py
invokust/aws_lambda/__init__.py
invokust/aws_lambda/lambda_load_test.py
invokust/aws_lambda/results_aggregator.py
invokust/aws_lambda/runtime_info.py
invokust-0.73.data/scripts/invokr.py
invokust-0.73.dist-info/LICENSE
invokust-0.73.dist-info/METADATA
invokust-0.73.dist-info/WHEEL
invokust-0.73.dist-info/top_level.txt
invokust-0.73.dist-info/RECORD
