Metadata-Version: 2.1
Name: invokust
Version: 0.73
Summary: A small wrapper for locust to allow running load tests from within Python or on AWS Lambda
Home-page: https://github.com/FutureSharks/invokust
Author: Max Williams
Author-email: futuresharks@gmail.com
License: MIT
Download-URL: https://github.com/FutureSharks/invokust/archive/0.73.tar.gz
Keywords: testing,loadtest,lamba,locust
Platform: UNKNOWN
Classifier: Topic :: Software Development :: Quality Assurance
Classifier: Topic :: Software Development :: Testing
Classifier: Topic :: Software Development :: Testing :: Traffic Generation
Classifier: Programming Language :: Python :: 3.6
Requires-Dist: locustio (==0.13.5)
Requires-Dist: boto3
Requires-Dist: pyzmq
Requires-Dist: numpy
